{
  "appInfo" : {
    "build" : "211.7142.13",
    "buildDate" : "2021-04-21T08:35:12.386Z[UTC]",
    "productCode" : "PC",
    "generated" : "2021-12-01T17:12:42.751264Z",
    "os" : "macOS 10.16",
    "runtime" : "JetBrains s.r.o. 11.0.10 11.0.10+9-b1341.41"
  },
  "runtimeInfo" : {
    "maxMemory" : 536870912,
    "numberOfProcessors" : 8,
    "maxNumberOfIndexingThreads" : 4,
    "maxSizeOfFileForIntelliSense" : 2560000,
    "maxSizeOfFileForContentLoading" : 20971520
  },
  "projectIndexingHistory" : {
    "projectName" : "all_repos_code_scripts",
    "times" : {
      "totalUpdatingTime" : 819447000,
      "indexingTime" : 0,
      "scanFilesTime" : 757496000,
      "pushPropertiesTime" : 2085000,
      "indexExtensionsTime" : 0,
      "updatingStart" : "2021-12-01T17:12:41.925536Z",
      "updatingEnd" : "2021-12-01T17:12:42.744983Z",
      "totalSuspendedTime" : 0,
      "wasInterrupted" : false
    },
    "totalStatsPerFileType" : [ ],
    "totalStatsPerIndexer" : [ ],
    "scanningStatistics" : [ {
      "providerName" : "com.intellij.javaee.ExternalResourcesRootsProvider@3a7db597",
      "numberOfScannedFiles" : 213,
      "numberOfSkippedFiles" : 4,
      "numberOfFilesForIndexing" : 0,
      "numberOfFilesFullyIndexedByInfrastructureExtensions" : 0,
      "scanningTime" : 651872704,
      "timeProcessingUpToDateFiles" : 15921932,
      "timeUpdatingContentLessIndexes" : 2720951,
      "timeIndexingWithoutContent" : 0
    }, {
      "providerName" : "com.intellij.ide.scratch.ScratchesAndConsolesIndexSetContributor@555ba863",
      "numberOfScannedFiles" : 0,
      "numberOfSkippedFiles" : 0,
      "numberOfFilesForIndexing" : 0,
      "numberOfFilesFullyIndexedByInfrastructureExtensions" : 0,
      "scanningTime" : 0,
      "timeProcessingUpToDateFiles" : 0,
      "timeUpdatingContentLessIndexes" : 0,
      "timeIndexingWithoutContent" : 0
    }, {
      "providerName" : "com.intellij.javaee.ExternalResourcesRootsProvider@3a7db597",
      "numberOfScannedFiles" : 0,
      "numberOfSkippedFiles" : 0,
      "numberOfFilesForIndexing" : 0,
      "numberOfFilesFullyIndexedByInfrastructureExtensions" : 0,
      "scanningTime" : 0,
      "timeProcessingUpToDateFiles" : 0,
      "timeUpdatingContentLessIndexes" : 0,
      "timeIndexingWithoutContent" : 0
    }, {
      "providerName" : "com.intellij.ide.scratch.ScratchesAndConsolesIndexSetContributor@555ba863",
      "numberOfScannedFiles" : 0,
      "numberOfSkippedFiles" : 0,
      "numberOfFilesForIndexing" : 0,
      "numberOfFilesFullyIndexedByInfrastructureExtensions" : 0,
      "scanningTime" : 0,
      "timeProcessingUpToDateFiles" : 0,
      "timeUpdatingContentLessIndexes" : 0,
      "timeIndexingWithoutContent" : 0
    } ],
    "fileProviderStatistics" : [ ]
  }
}