{
  "appInfo" : {
    "build" : "211.7142.13",
    "buildDate" : "2021-04-21T08:35:03.858Z[UTC]",
    "productCode" : "PC",
    "generated" : "2021-12-01T19:03:34.100023Z",
    "os" : "macOS 10.16",
    "runtime" : "JetBrains s.r.o. 11.0.10 11.0.10+9-b1341.41"
  },
  "runtimeInfo" : {
    "maxMemory" : 536870912,
    "numberOfProcessors" : 8,
    "maxNumberOfIndexingThreads" : 4,
    "maxSizeOfFileForIntelliSense" : 2560000,
    "maxSizeOfFileForContentLoading" : 20971520
  },
  "projectIndexingHistory" : {
    "projectName" : "all_repos_code_scripts",
    "times" : {
      "totalUpdatingTime" : 1052952000,
      "indexingTime" : 0,
      "scanFilesTime" : 858993000,
      "pushPropertiesTime" : 1747000,
      "indexExtensionsTime" : 0,
      "updatingStart" : "2021-12-01T19:03:33.038096Z",
      "updatingEnd" : "2021-12-01T19:03:34.091048Z",
      "totalSuspendedTime" : 0,
      "wasInterrupted" : false
    },
    "totalStatsPerFileType" : [ ],
    "totalStatsPerIndexer" : [ ],
    "scanningStatistics" : [ {
      "providerName" : "com.intellij.javaee.ExternalResourcesRootsProvider@11717e5c",
      "numberOfScannedFiles" : 213,
      "numberOfSkippedFiles" : 4,
      "numberOfFilesForIndexing" : 0,
      "numberOfFilesFullyIndexedByInfrastructureExtensions" : 0,
      "scanningTime" : 711608462,
      "timeProcessingUpToDateFiles" : 17225579,
      "timeUpdatingContentLessIndexes" : 3779531,
      "timeIndexingWithoutContent" : 0
    }, {
      "providerName" : "com.intellij.ide.scratch.ScratchesAndConsolesIndexSetContributor@64418d26",
      "numberOfScannedFiles" : 0,
      "numberOfSkippedFiles" : 0,
      "numberOfFilesForIndexing" : 0,
      "numberOfFilesFullyIndexedByInfrastructureExtensions" : 0,
      "scanningTime" : 0,
      "timeProcessingUpToDateFiles" : 0,
      "timeUpdatingContentLessIndexes" : 0,
      "timeIndexingWithoutContent" : 0
    }, {
      "providerName" : "com.intellij.javaee.ExternalResourcesRootsProvider@11717e5c",
      "numberOfScannedFiles" : 0,
      "numberOfSkippedFiles" : 0,
      "numberOfFilesForIndexing" : 0,
      "numberOfFilesFullyIndexedByInfrastructureExtensions" : 0,
      "scanningTime" : 0,
      "timeProcessingUpToDateFiles" : 0,
      "timeUpdatingContentLessIndexes" : 0,
      "timeIndexingWithoutContent" : 0
    }, {
      "providerName" : "com.intellij.ide.scratch.ScratchesAndConsolesIndexSetContributor@64418d26",
      "numberOfScannedFiles" : 0,
      "numberOfSkippedFiles" : 0,
      "numberOfFilesForIndexing" : 0,
      "numberOfFilesFullyIndexedByInfrastructureExtensions" : 0,
      "scanningTime" : 0,
      "timeProcessingUpToDateFiles" : 0,
      "timeUpdatingContentLessIndexes" : 0,
      "timeIndexingWithoutContent" : 0
    } ],
    "fileProviderStatistics" : [ ]
  }
}